README.md
setup.py
dognames/__init__.py
dognames.egg-info/PKG-INFO
dognames.egg-info/SOURCES.txt
dognames.egg-info/dependency_links.txt
dognames.egg-info/top_level.txt