Metadata-Version: 2.1
Name: dognames
Version: 0.0.2
Summary: Get Awesome Random dog names!
Home-page: https://yoginth.ml
Author: Yoginth
Author-email: yoginth@zoho.com
License: UNKNOWN
Project-URL: Patreon, https://www.patreon.com/yoginth
Project-URL: Source, https://gitlab.com/yoginth/dognames
Platform: UNKNOWN
Classifier: Programming Language :: Python
Classifier: Natural Language :: English
Classifier: Environment :: Plugins
Classifier: Operating System :: OS Independent
Classifier: Intended Audience :: Developers
Classifier: License :: OSI Approved :: MIT License
